yolo_convert/__init__.py
yolo_convert/cli.py
yolo_convert/yolov5/EfficientNMS.py
yolo_convert/yolov5/benchmarks.py
yolo_convert/yolov5/detect.py
yolo_convert/yolov5/export.py
yolo_convert/yolov5/export_onnx.py
yolo_convert/yolov5/global_config.py
yolo_convert/yolov5/hubconf.py
yolo_convert/yolov5/modify_model.py
yolo_convert/yolov5/train.py
yolo_convert/yolov5/val.py
yolo_convert/yolov5/classify/predict.py
yolo_convert/yolov5/classify/train.py
yolo_convert/yolov5/classify/val.py
yolo_convert/yolov5/models/__init__.py
yolo_convert/yolov5/models/common.py
yolo_convert/yolov5/models/experimental.py
yolo_convert/yolov5/models/tf.py
yolo_convert/yolov5/models/yolo.py
yolo_convert/yolov5/rpn_op/dec_bbox.py
yolo_convert/yolov5/rpn_op/filter.py
yolo_convert/yolov5/rpn_op/nms.py
yolo_convert/yolov5/rpn_op/sort.py
yolo_convert/yolov5/segment/predict.py
yolo_convert/yolov5/segment/train.py
yolo_convert/yolov5/segment/val.py
yolo_convert/yolov5/utils/__init__.py
yolo_convert/yolov5/utils/activations.py
yolo_convert/yolov5/utils/augmentations.py
yolo_convert/yolov5/utils/autoanchor.py
yolo_convert/yolov5/utils/autobatch.py
yolo_convert/yolov5/utils/callbacks.py
yolo_convert/yolov5/utils/dataloaders.py
yolo_convert/yolov5/utils/downloads.py
yolo_convert/yolov5/utils/general.py
yolo_convert/yolov5/utils/loss.py
yolo_convert/yolov5/utils/metrics.py
yolo_convert/yolov5/utils/plots.py
yolo_convert/yolov5/utils/torch_utils.py
yolo_convert/yolov5/utils/triton.py
yolo_convert/yolov5/utils/aws/__init__.py
yolo_convert/yolov5/utils/aws/resume.py
yolo_convert/yolov5/utils/flask_rest_api/example_request.py
yolo_convert/yolov5/utils/flask_rest_api/restapi.py
yolo_convert/yolov5/utils/loggers/__init__.py
yolo_convert/yolov5/utils/loggers/clearml/__init__.py
yolo_convert/yolov5/utils/loggers/clearml/clearml_utils.py
yolo_convert/yolov5/utils/loggers/clearml/hpo.py
yolo_convert/yolov5/utils/loggers/comet/__init__.py
yolo_convert/yolov5/utils/loggers/comet/comet_utils.py
yolo_convert-0.1.6.dist-info/METADATA
yolo_convert-0.1.6.dist-info/WHEEL
yolo_convert-0.1.6.dist-info/entry_points.txt
yolo_convert-0.1.6.dist-info/top_level.txt
yolo_convert-0.1.6.dist-info/RECORD
