Metadata-Version: 2.4
Name: yolo-convert
Version: 0.1.6
Summary: YOLOv5 model conversion CLI
Author: hankobeo
License: MIT
Requires-Dist: torch>=1.8
Requires-Dist: onnx
